theos_ai-0.0.36.dist-info/METADATA
theos_ai-0.0.36.dist-info/entry_points.txt
theos_ai-0.0.36.dist-info/WHEEL
theos_ai-0.0.36.dist-info/RECORD
theos_ai-0.0.36.dist-info/top_level.txt
theos/client.cpython-310-i386-linux-gnu.so
theos/__main__.cpython-310-i386-linux-gnu.so
theos/api.cpython-310-i386-linux-gnu.so
theos/exceptions.cpython-310-i386-linux-gnu.so
theos/__init__.cpython-310-i386-linux-gnu.so
theos/__internal/cli.cpython-310-i386-linux-gnu.so
theos/__internal/__init__.cpython-310-i386-linux-gnu.so
theos/__internal/decorators.cpython-310-i386-linux-gnu.so
theos/__internal/connectors/errors.cpython-310-i386-linux-gnu.so
theos/__internal/connectors/constants.cpython-310-i386-linux-gnu.so
theos/__internal/connectors/algorithm.cpython-310-i386-linux-gnu.so
theos/__internal/connectors/dataset.cpython-310-i386-linux-gnu.so
theos/__internal/connectors/exceptions.cpython-310-i386-linux-gnu.so
theos/__internal/connectors/machines.cpython-310-i386-linux-gnu.so
theos/__internal/connectors/__init__.cpython-310-i386-linux-gnu.so
theos/__internal/connectors/config.cpython-310-i386-linux-gnu.so
theos/__internal/connectors/user/authentication.cpython-310-i386-linux-gnu.so
theos/__internal/connectors/user/__init__.cpython-310-i386-linux-gnu.so
theos/__internal/connectors/user/profile.cpython-310-i386-linux-gnu.so
theos/__internal/utils/websocket.cpython-310-i386-linux-gnu.so
theos/__internal/utils/log.cpython-310-i386-linux-gnu.so
theos/__internal/utils/other.cpython-310-i386-linux-gnu.so
theos/__internal/utils/http.cpython-310-i386-linux-gnu.so
theos/__internal/utils/system.cpython-310-i386-linux-gnu.so
theos/__internal/utils/algorithms.cpython-310-i386-linux-gnu.so
theos/__internal/utils/__init__.cpython-310-i386-linux-gnu.so
theos/__internal/utils/asserts.cpython-310-i386-linux-gnu.so
theos/__internal/utils/docker/client.cpython-310-i386-linux-gnu.so
theos/__internal/utils/docker/image.cpython-310-i386-linux-gnu.so
theos/__internal/utils/docker/container.cpython-310-i386-linux-gnu.so
theos/__internal/utils/docker/exceptions.cpython-310-i386-linux-gnu.so
theos/__internal/utils/docker/__init__.cpython-310-i386-linux-gnu.so
