Metadata-Version: 2.1
Name: theos-ai
Version: 0.0.36
Summary: Theos
Home-page: https://theos.ai
Author: theos
Author-email: contact@theos.ai
License: Other/Proprietary License
Keywords: theos
Classifier: Development Status :: 3 - Alpha
Classifier: Intended Audience :: Developers
Classifier: Topic :: Software Development :: Build Tools
Classifier: License :: Other/Proprietary License
Classifier: Programming Language :: Python :: 3.6
Classifier: Programming Language :: Python :: 3.7
Classifier: Programming Language :: Python :: 3.8
Classifier: Programming Language :: Python :: 3.9
Requires-Dist: Pillow (==8.3.2)
Requires-Dist: python-socketio (==5.3.0)
Requires-Dist: psutil (==5.8.0)
Requires-Dist: GPUtil (==1.4.0)
Requires-Dist: urllib3 (==1.26.7)
Requires-Dist: requests (==2.25.0)
Requires-Dist: httpx (==0.18.0)
Requires-Dist: aiofiles (==0.6.0)
Requires-Dist: docker (==4.3.1)
Requires-Dist: opencv-python (==4.6.0.66)
Requires-Dist: distro (==1.5.0)
Requires-Dist: matplotlib (==3.5.3)
Requires-Dist: colorama (==0.4.4)
Requires-Dist: yaspin (==1.1.0)
Requires-Dist: tqdm (==4.48.0)
Requires-Dist: Flask-SocketIO (==5.1.0)
Requires-Dist: SQLAlchemy (==1.3.22)
Requires-Dist: websockets (==10.3)
Requires-Dist: PyYAML (==6.0.1)
Requires-Dist: py-cpuinfo (==8.0.0)
Requires-Dist: imagesize (==1.2.0)
Requires-Dist: nest-asyncio (==1.5.6)
Requires-Dist: shutup (==0.2.0)
Provides-Extra: ocr
Requires-Dist: keras-ocr (==0.8.9) ; extra == 'ocr'
Requires-Dist: transformers (==4.22.1) ; extra == 'ocr'
Requires-Dist: sentencepiece (==0.1.97) ; extra == 'ocr'
Requires-Dist: pytesseract (==0.3.10) ; extra == 'ocr'
Provides-Extra: sdk
Requires-Dist: redis (==3.5.3) ; extra == 'sdk'
Requires-Dist: celery (==5.0.0) ; extra == 'sdk'
Requires-Dist: gevent-websocket (==0.10.1) ; extra == 'sdk'
